{
  "algorithm_name": "single",
  "instance": 2102,
  "population": 50,
  "run_id": 11,
  "dimension": 42,
  "budget": 10000,
  "seed": 2128,
  "selection": "tournament",
  "lines_written": 10009,
  "best_so_far": 71.0,
  "start_time": "2025-11-02T13:15:01.457443",
  "end_time": "2025-11-02T13:15:01.489587",
  "platform": "Linux-6.6.87.2-microsoft-standard-WSL2-x86_64-with-glibc2.35",
  "python_version": "3.11.13",
  "hostname": "Manith",
  "variant": "populationEA",
  "elapsed_seconds": 0.03158426284790039,
  "algorithm_type": "PopulationEA",
  "run_summary_best": 46.0
}