{
  "algorithm_name": "multi",
  "instance": 2100,
  "population": 10,
  "run_id": 12,
  "dimension": 40,
  "budget": 10000,
  "seed": 1609,
  "selection": "uniform",
  "lines_written": 10000,
  "best_so_far": 77.0,
  "start_time": "2025-11-02T13:12:24.487566",
  "end_time": "2025-11-02T13:12:24.642095",
  "platform": "Linux-6.6.87.2-microsoft-standard-WSL2-x86_64-with-glibc2.35",
  "python_version": "3.11.13",
  "hostname": "Manith",
  "variant": "PopulationGSEMO",
  "elapsed_seconds": 0.15361595153808594,
  "algorithm_type": "PopulationGSEMO",
  "run_summary_best": 11.0
}